examples/dataset_hub_example.py
examples/meta_learning.py
examples/transfer_learning.py
examples/unsupervised_learning.py
examples/webassembly_integration.py
neurenix/__init__.py
neurenix/api_support.py
neurenix/binding.py
neurenix/core.py
neurenix/device.py
neurenix/device_manager.py
neurenix/onnx_support.py
neurenix/quantization.py
neurenix/tensor.py
neurenix/utils.py
neurenix/agent/__init__.py
neurenix/agent/agent.py
neurenix/agent/environment.py
neurenix/agent/multi_agent.py
neurenix/async_train/__init__.py
neurenix/async_train/async_trainer.py
neurenix/async_train/checkpoint.py
neurenix/async_train/distributed.py
neurenix/async_train/resume.py
neurenix/automl/__init__.py
neurenix/automl/model_selection.py
neurenix/automl/nas.py
neurenix/automl/pipeline.py
neurenix/automl/search.py
neurenix/cli/__init__.py
neurenix/cli/__main__.py
neurenix/cli/cli.py
neurenix/cli/commands/__init__.py
neurenix/cli/commands/dataset.py
neurenix/cli/commands/eval.py
neurenix/cli/commands/export.py
neurenix/cli/commands/hardware.py
neurenix/cli/commands/help.py
neurenix/cli/commands/init.py
neurenix/cli/commands/monitor.py
neurenix/cli/commands/optimize.py
neurenix/cli/commands/predict.py
neurenix/cli/commands/preprocess.py
neurenix/cli/commands/run.py
neurenix/cli/commands/save.py
neurenix/cli/commands/serve.py
neurenix/continual/__init__.py
neurenix/continual/distillation.py
neurenix/continual/ewc.py
neurenix/continual/regularization.py
neurenix/continual/replay.py
neurenix/continual/synaptic.py
neurenix/data/__init__.py
neurenix/data/arrow.py
neurenix/data/dataset_hub.py
neurenix/data/parquet.py
neurenix/distributed/__init__.py
neurenix/distributed/dask_integration.py
neurenix/distributed/data_parallel.py
neurenix/distributed/deepspeed.py
neurenix/distributed/distributed.py
neurenix/distributed/dotnet.py
neurenix/distributed/grpc_streaming.py
neurenix/distributed/horovod.py
neurenix/distributed/mpi.py
neurenix/distributed/pycuda_integration.py
neurenix/distributed/rpc.py
neurenix-2.0.1.dist-info/licenses/LICENSE
neurenix-2.0.1.dist-info/METADATA
neurenix-2.0.1.dist-info/WHEEL
neurenix-2.0.1.dist-info/entry_points.txt
neurenix-2.0.1.dist-info/top_level.txt
neurenix-2.0.1.dist-info/RECORD
