Metadata-Version: 2.4
Name: neurenix
Version: 2.0.1
Summary: Empowering Intelligent Futures, One Edge at a Time.
Author-email: Neurenix Team <packages@milesonerd.8shield.net>
License: Apache-2.0
Project-URL: Homepage, https://neurenix.github.io
Project-URL: Source Code, https://github.com/MilesONerd/neurenix
Project-URL: Download, https://pypi.org/project/neurenix/#files
Project-URL: Bug Tracker, https://github.com/MilesONerd/neurenix/issues
Project-URL: Documentation, https://neurenix.readthedocs.io/en/latest/
Project-URL: Community, https://discord.gg/Eqnhr8tK2G
Keywords: machine learning,deep learning,neural networks,AI,edge computing,reinforcement learning,agents,AGI
Classifier: Development Status :: 3 - Alpha
Classifier: Intended Audience :: Developers
Classifier: Intended Audience :: Science/Research
Classifier: License :: OSI Approved :: Apache Software License
Classifier: Programming Language :: Python :: 3
Classifier: Programming Language :: Python :: 3.8
Classifier: Programming Language :: Python :: 3.9
Classifier: Programming Language :: Python :: 3.10
Classifier: Programming Language :: Python :: 3.11
Classifier: Programming Language :: Python :: 3.12
Classifier: Programming Language :: Python :: 3.13
Classifier: Programming Language :: Python :: 3.14
Classifier: Programming Language :: Python :: Implementation :: CPython
Classifier: Programming Language :: Rust
Classifier: Programming Language :: C++
Classifier: Programming Language :: Go
Classifier: Programming Language :: C#
Classifier: Topic :: Scientific/Engineering
Classifier: Topic :: Scientific/Engineering :: Artificial Intelligence
Classifier: Topic :: Software Development :: Libraries
Classifier: Topic :: Scientific/Engineering :: Quantum Computing
Classifier: Topic :: System :: Clustering
Classifier: Topic :: System :: Distributed Computing
Classifier: Topic :: System :: Hardware
Classifier: Environment :: GPU
Classifier: Environment :: WebAssembly
Requires-Python: >=3.8
License-File: LICENSE
Requires-Dist: numpy>=1.24.0
Requires-Dist: typing-extensions>=4.7.0
Requires-Dist: scipy>=1.10.0
Provides-Extra: dev
Requires-Dist: pytest>=7.4.0; extra == "dev"
Requires-Dist: pytest-cov>=4.1.0; extra == "dev"
Requires-Dist: black>=23.7.0; extra == "dev"
Requires-Dist: isort>=5.12.0; extra == "dev"
Requires-Dist: mypy>=1.5.0; extra == "dev"
Provides-Extra: cuda
Requires-Dist: pycuda>=2022.1; extra == "cuda"
Provides-Extra: distributed
Requires-Dist: ray>=2.0.0; extra == "distributed"
Provides-Extra: agents
Requires-Dist: gymnasium>=0.28.0; extra == "agents"
Provides-Extra: huggingface
Requires-Dist: transformers>=4.0.0; extra == "huggingface"
Requires-Dist: datasets>=2.0.0; extra == "huggingface"
Dynamic: license-file
